{
	"configurations" : 
	[
		{
			"directories" : 
			[
				{
					"build" : ".",
					"childIndexes" : 
					[
						1
					],
					"jsonFile" : "directory-.-Debug-f5ebdc15457944623624.json",
					"minimumCMakeVersion" : 
					{
						"string" : "3.16"
					},
					"projectIndex" : 0,
					"source" : ".",
					"targetIndexes" : 
					[
						1,
						2
					]
				},
				{
					"build" : "external/gflags",
					"jsonFile" : "directory-external.gflags-Debug-a0c1881e46f5cc71c7b0.json",
					"minimumCMakeVersion" : 
					{
						"string" : "3.5"
					},
					"parentIndex" : 0,
					"projectIndex" : 1,
					"source" : "external/gflags",
					"targetIndexes" : 
					[
						0
					]
				}
			],
			"name" : "Debug",
			"projects" : 
			[
				{
					"childIndexes" : 
					[
						1
					],
					"directoryIndexes" : 
					[
						0
					],
					"name" : "TisaSimulator",
					"targetIndexes" : 
					[
						1,
						2
					]
				},
				{
					"directoryIndexes" : 
					[
						1
					],
					"name" : "gflags",
					"parentIndex" : 0,
					"targetIndexes" : 
					[
						0
					]
				}
			],
			"targets" : 
			[
				{
					"directoryIndex" : 1,
					"id" : "gflags_nothreads_static::@39a3b937ccb9c0984652",
					"jsonFile" : "target-gflags_nothreads_static-Debug-835fff50f7b1bacfec79.json",
					"name" : "gflags_nothreads_static",
					"projectIndex" : 1
				},
				{
					"directoryIndex" : 0,
					"id" : "sim.out::@6890427a1f51a3e7e1df",
					"jsonFile" : "target-sim.out-Debug-e45301407d694385c4ac.json",
					"name" : "sim.out",
					"projectIndex" : 0
				},
				{
					"directoryIndex" : 0,
					"id" : "sim_tests.out::@6890427a1f51a3e7e1df",
					"jsonFile" : "target-sim_tests.out-Debug-b636e467610fc00f3fb9.json",
					"name" : "sim_tests.out",
					"projectIndex" : 0
				}
			]
		}
	],
	"kind" : "codemodel",
	"paths" : 
	{
		"build" : "/home/vboxuser/sim-course/lab1/build",
		"source" : "/home/vboxuser/sim-course/lab1"
	},
	"version" : 
	{
		"major" : 2,
		"minor" : 3
	}
}
